cget/__main__.py
choco_get-2.dist-info/METADATA
choco_get-2.dist-info/WHEEL
choco_get-2.dist-info/entry_points.txt
choco_get-2.dist-info/top_level.txt
choco_get-2.dist-info/RECORD
