Metadata-Version: 2.2
Name: choco-get
Version: 2
Summary: A fast replacement for wget.
Author: Chocolateisfr
License: MIT
Classifier: Programming Language :: Python :: 3
Classifier: License :: OSI Approved :: MIT License
Classifier: Operating System :: OS Independent
Requires-Python: >=3.7
Requires-Dist: rich
